{"extracted_information": "一份简历是对个人能力、教育背景和经验的简洁、信息丰富的总结。它应突出个人最强的优势和技能，并使其与其他求职者区分开来。虽然简历本身不能让你获得工作或实习，但一份好的简历是获得面试的重要因素。请根据所申请的职位类型来定制简历，这意味着简历应体现雇主看重的技能类型。", "specifications": {}, "pricing": {}, "features": [{"category": "简历语言原则", "items": ["具体而非笼统", "主动而非被动", "旨在表达而非炫耀", "清晰而非“华丽”", "基于事实（量化和限定）", "为快速扫描的系统和人员撰写"]}, {"category": "简历的五大常见错误", "items": ["拼写和语法错误", "缺少电子邮件和电话信息", "使用被动语态而非“行动”词", "组织不佳、不简洁或难以快速浏览", "未能展示成果"]}, {"category": "简历不应包含的", "items": ["使用人称代词（如“我”或“我们”）", "使用缩写", "采用叙述风格", "使用俚语或口语", "包含照片", "包含年龄或性别", "列出推荐人", "每行都以日期开头"]}, {"category": "简历应包含的", "items": ["格式和内容保持一致性", "易于阅读和理解，并保持适当的留白", "使用一致的间距、下划线、斜体、粗体和大写来强调", "标题（如“经验”）按重要性顺序排列", "在每个标题下，信息按时间倒序排列（最近的在前）", "避免信息空白，例如缺少某个夏季的经历", "确保转换为.pdf文件时，格式能正确转换"]}, {"category": "使用AI的建议", "items": ["AI可作为编辑工具（如头脑风暴修改要点、整合关键词）", "AI不应是主要作者（输出可能非常通用）", "应真实地代表自己"]}, {"category": "行动词示例", "types": [{"type": "领导力", "words": ["Accomplished", "Achieved", "Administered", "Analyzed", "Assigned", "Attained", "Chaired", "Consolidated", "Contracted", "Coordinated", "Delegated", "Developed", "Directed", "Earned", "Evaluated", "Executed", "Handled", "Headed", "Impacted", "Improved", "Increased", "Led", "Mastered", "Orchestrated", "Organized", "Oversaw", "Planned", "Predicted", "Prioritized", "Produced", "Proved", "Recommended", "Regulated", "Reorganized", "Reviewed", "Scheduled", "Spearheaded", "Strengthened", "Supervised", "Surpassed"]}, {"type": "沟通", "words": ["Addressed", "Arbitrated", "Arranged", "Authored", "Collaborated", "Convinced", "Corresponded", "Delivered", "Developed", "Directed", "Documented", "Drafted", "Edited", "Energized", "Enlisted", "Formulated", "Influenced", "Interpreted", "Lectured", "Liaised", "Mediated", "Moderated", "Negotiated", "Persuaded", "Presented", "Promoted", "Publicized", "Reconciled", "Recruited", "Reported", "Rewrote", "Spoke", "Suggested", "Synthesized", "Translated", "Verbalized", "Wrote"]}, {"type": "研究", "words": ["Clarified", "Collected", "Concluded", "Conducted", "Constructed", "Critiqued", "Derived", "Determined", "Diagnosed", "Discovered", "Evaluated", "Examined", "Extracted", "Formed", "Identified", "Inspected", "Interpreted", "Interviewed", "Investigated", "Modeled", "Organized", "Resolved", "Reviewed", "Summarized", "Surveyed", "Systematized", "Tested"]}, {"type": "技术", "words": ["Assembled", "Built", "Calculated", "Computed", "Designed", "Devised", "Engineered", "Fabricated", "Installed", "Maintained", "Operated", "Optimized", "Overhauled", "Programmed", "Remodeled", "Repaired", "Solved", "Standardized", "Streamlined", "Upgraded"]}, {"type": "教学", "words": ["Adapted", "Advised", "Clarified", "Coached", "Communicated", "Coordinated", "Demystified", "Developed", "Enabled", "Encouraged", "Evaluated", "Explained", "Facilitated", "Guided", "Informed", "Instructed", "Persuaded", "Set Goals", "Stimulated", "Studied", "Taught", "Trained"]}, {"type": "量化", "words": ["Administered", "Allocated", "Analyzed", "Appraised", "Audited", "Balanced", "Budgeted", "Calculated", "Computed", "Developed", "Forecasted", "Managed", "Marketed", "Maximized", "Minimized", "Planned", "Projected", "Researched"]}, {"type": "创意", "words": ["Acted", "Composed", "Conceived", "Conceptualized", "Created", "Customized", "Designed", "Developed", "Directed", "Established", "Fashioned", "Founded", "Illustrated", "Initiated", "Instituted", "Integrated", "Introduced", "Invented", "Originated", "Performed", "Planned", "Published", "Redesigned", "Revised", "Revitalized", "Shaped", "Visualized"]}, {"type": "帮助", "words": ["Assessed", "Assisted", "Clarified", "Coached", "Counseled", "Demonstrated", "Diagnosed", "Educated", "Enhanced", "Expedited", "Facilitated", "Familiarized", "Guided", "Motivated", "Participated", "Proposed", "Provided", "Referred", "Rehabilitated", "Represented", "Served", "Supported"]}, {"type": "组织", "words": ["Approved", "Accelerated", "Added", "Arranged", "Broadened", "Cataloged", "Centralized", "Changed", "Classified", "Collected", "Compiled", "Completed", "Controlled", "Defined", "Dispatched", "Executed", "Expanded", "Gained", "Gathered", "Generated", "Implemented", "Inspected", "Launched", "Monitored", "Operated", "Organized", "Prepared", "Processed", "Purchased", "Recorded", "Reduced", "Reinforced", "Retrieved", "Screened", "Selected", "Simplified", "Sold", "Specified", "Steered", "Structured", "Systematized", "Tabulated", "Unified", "Updated", "Utilized", "Validated", "Verified"]}]}], "statistics": {}, "temporal_info": {}, "geographical_data": {}, "references": []}